[
  {
    "ParameterKey": "ProjectName",
    "ParameterValue": "my-project",
    "UsePreviousValue": false
  },
  {
    "ParameterKey": "EnvironmentName",
    "ParameterValue": "development",
    "UsePreviousValue": false
  },
  {
    "ParameterKey": "S3DeploymentBucketName",
    "ParameterValue": "andlytle-deployments",
    "UsePreviousValue": false
  },
  {
    "ParameterKey": "S3DeploymentFileKey",
    "ParameterValue": "/lambda/my-project.zip",
    "UsePreviousValue": false
  },
  {
    "ParameterKey": "ScheduleExpression",
    "ParameterValue": "rate(24 hours)",
    "UsePreviousValue": false
  },
  {
    "ParameterKey": "Runtime",
    "ParameterValue": "python2.7",
    "UsePreviousValue": false
  },
  {
    "ParameterKey": "Timeout",
    "ParameterValue": "300",
    "UsePreviousValue": false
  },
  {
    "ParameterKey": "MemorySize",
    "ParameterValue": "256",
    "UsePreviousValue": false
  }
]
